qgear_lightning/__init__.py
qgear_lightning/_modidx.py
qgear_lightning/core.py
qgear_lightning/io.py
qgear_lightning-1.0.0.dist-info/LICENSE
qgear_lightning-1.0.0.dist-info/METADATA
qgear_lightning-1.0.0.dist-info/WHEEL
qgear_lightning-1.0.0.dist-info/entry_points.txt
qgear_lightning-1.0.0.dist-info/top_level.txt
qgear_lightning-1.0.0.dist-info/RECORD
