Metadata-Version: 2.1
Name: qgear-lightning
Version: 1.0.0
Summary: qgear-lightning
Home-page: https://github.com/gzquse/qgear-lightning
Author: ziqing
Author-email: ziqinguse@gmail.com
License: Apache Software License 2.0
Keywords: nbdev jupyter notebook python
Platform: UNKNOWN
Classifier: Development Status :: 4 - Beta
Classifier: Intended Audience :: Developers
Classifier: Natural Language :: English
Classifier: Programming Language :: Python :: 3.7
Classifier: Programming Language :: Python :: 3.8
Classifier: Programming Language :: Python :: 3.9
Classifier: Programming Language :: Python :: 3.10
Classifier: Programming Language :: Python :: 3.11
Classifier: Programming Language :: Python :: 3.12
Classifier: License :: OSI Approved :: Apache Software License
Requires-Python: >=3.7
License-File: LICENSE
Requires-Dist: cudaq
Requires-Dist: h5py
Requires-Dist: numpy
Requires-Dist: pillow
Requires-Dist: qiskit
Provides-Extra: dev
Requires-Dist: jupyterlab ; extra == 'dev'
Requires-Dist: nbdev ; extra == 'dev'
Requires-Dist: pennylane ; extra == 'dev'
